[{"id":2701,"type":"single","question":"Čo je beletrizovaný životopis?","options":["Hybridný útvar spájajúci príbeh, opis a fakty","Čisto úradný a vecný životopis","Iba stručný zoznam životných údajov","Výlučne odborný text bez emócií"],"correctAnswer":"Hybridný útvar spájajúci príbeh, opis a fakty"},{"id":2702,"type":"single","question":"Prečo sa beletrizovaný životopis označuje ako hybridný útvar?","options":["Spája umelecký, opisný, rozprávací aj informačný postup","Vzniká iba spojením dvoch úradných formulárov","Je napísaný súčasne v dvoch jazykoch","Obsahuje len fakty a žiadnu štylizáciu"],"correctAnswer":"Spája umelecký, opisný, rozprávací aj informačný postup"},{"id":2703,"type":"single","question":"V čom sa beletrizovaný životopis odlišuje od úradného?","options":["Môže byť subjektívny, obrazný a čiastočne fikčný","Musí byť ešte stručnejší a heslovitejší","Nemá obsahovať žiadne fakty","Píše sa iba v 3. osobe"],"correctAnswer":"Môže byť subjektívny, obrazný a čiastočne fikčný"},{"id":2704,"type":"multiple","question":"Aké sú základné znaky beletrizovaného životopisu?","options":["príbehovosť","faktografickosť","subjektívnosť","emocionálnosť","pútavosť","schematickosť"],"correctAnswer":["príbehovosť","faktografickosť","subjektívnosť","emocionálnosť","pútavosť"]},{"id":2705,"type":"single","question":"Koľko faktov zo života by mal minimálne obsahovať?","options":["Aspoň päť","Aspoň dva","Presne desať","Nemusí obsahovať nijaké"],"correctAnswer":"Aspoň päť"},{"id":2706,"type":"multiple","question":"Ktoré fakty sa odporúča zakomponovať do beletrizovaného životopisu?","options":["narodenie","rodinné zázemie","štúdium","zlomová udalosť","záujmy","budúce ambície"],"correctAnswer":["narodenie","rodinné zázemie","štúdium","zlomová udalosť","záujmy","budúce ambície"]},{"id":2707,"type":"single","question":"V akej osobe sa beletrizovaný životopis píše?","options":["V 1. osobe alebo v 3. osobe","Iba v 1. osobe","Iba v 2. osobe","Výlučne v neurčitku"],"correctAnswer":"V 1. osobe alebo v 3. osobe"},{"id":2708,"type":"single","question":"Aký slohový postup v beletrizovanom životopise dominuje?","options":["Rozprávací a opisný","Administratívny a náučný","Iba informačný","Len rečnícky"],"correctAnswer":"Rozprávací a opisný"},{"id":2709,"type":"ordering","question":"Usporiadaj základnú kompozíciu beletrizovaného životopisu.","options":["úvod","jadro","záver"],"correctAnswer":["úvod","jadro","záver"]},{"id":2710,"type":"single","question":"Čo patrí do úvodu beletrizovaného životopisu?","options":["Vstupné priblíženie osoby a prostredia","Iba presný dátum a miesto narodenia bez štylizácie","Výlučne budúce plány a sny","Zoznam záujmov v bodoch"],"correctAnswer":"Vstupné priblíženie osoby a prostredia"},{"id":2711,"type":"single","question":"Čo patrí do jadra beletrizovaného životopisu?","options":["Najdôležitejšie životné fakty a etapy","Len citáty a prirovnania","Iba úradné formulácie","Výlučne záverečné hodnotenie"],"correctAnswer":"Najdôležitejšie životné fakty a etapy"},{"id":2712,"type":"single","question":"Čo patrí do záveru beletrizovaného životopisu?","options":["Hodnotenie života, sny a ambície","Presný prepis rodného listu","Iba zoznam škôl a dátumov","Podpis a miesto vyhotovenia"],"correctAnswer":"Hodnotenie života, sny a ambície"},{"id":2713,"type":"multiple","question":"Aké jazykové prostriedky sa v beletrizovanom životopise využívajú?","options":["spisovné a neutrálne slová","citovo zafarbené slová","hovorové výrazy","slang","umelecké jazykové prostriedky","iba úradné klišé"],"correctAnswer":["spisovné a neutrálne slová","citovo zafarbené slová","hovorové výrazy","slang","umelecké jazykové prostriedky"]},{"id":2714,"type":"multiple","question":"Ktoré umelecké prostriedky sa môžu objaviť v beletrizovanom životopise?","options":["metafory","personifikácie","epitetá","prirovnania","kontrast","iba značky a skratky"],"correctAnswer":["metafory","personifikácie","epitetá","prirovnania","kontrast"]},{"id":2715,"type":"multiple","question":"Vyber správne tvrdenia o beletrizovanom životopise.","options":["môže byť humorný","autor môže pracovať aj s fikciou","je príbehový","je čisto úradný a strohý","nemal by obsahovať žiadne fakty"],"correctAnswer":["môže byť humorný","autor môže pracovať aj s fikciou","je príbehový"]},{"id":2716,"type":"single","question":"Ako možno porovnať beletrizovaný a úradný životopis?","options":["Úradný je vecný, beletrizovaný je obrazný a príbehový","Úradný je obrazný, beletrizovaný je úplne strohý","Oba sú úplne rovnaké","Úradný je vždy dlhší a osobnejší"],"correctAnswer":"Úradný je vecný, beletrizovaný je obrazný a príbehový"},{"id":2717,"type":"matching","question":"Priraď časť kompozície k obsahu.","pairs":[{"term":"úvod","match":"základné priblíženie osoby"},{"term":"jadro","match":"životné fakty a etapy"},{"term":"záver","match":"ambície a hodnotenie"}],"correctAnswer":{"úvod":"základné priblíženie osoby","jadro":"životné fakty a etapy","záver":"ambície a hodnotenie"}},{"id":2718,"type":"ordering","question":"Usporiadaj vhodný chronologický plán beletrizovaného životopisu.","options":["narodenie","štúdium","zlomová udalosť","záujmy","budúce plány"],"correctAnswer":["narodenie","štúdium","zlomová udalosť","záujmy","budúce plány"]},{"id":2719,"type":"single","question":"Ktorá veta by mohla patriť do beletrizovaného životopisu?","options":["Narodil som sa v daždivé augustové ráno.","Meno: Samuel. Dátum: 5. august.","Bydlisko: Snina. Telefón: uvedený.","Vzdelanie: základné. Zručnosti: bežné."],"correctAnswer":"Narodil som sa v daždivé augustové ráno."},{"id":2720,"type":"multiple","question":"Ktoré slohové postupy sa môžu v beletrizovanom životopise kombinovať?","options":["opisný","rozprávací","informačný","výkladový","iba administratívny"],"correctAnswer":["opisný","rozprávací","informačný","výkladový"]},{"id":2721,"type":"single","question":"Aké špecifické črty má slovenská dramatická tvorba po roku 1945?","options":["Rozšírila sa sieť divadiel a silné boli najmä 60. roky","Úplne zanikla a nehrala sa","Rozvíjala sa len ľudová veselohra","Vznikala iba v exile"],"correctAnswer":"Rozšírila sa sieť divadiel a silné boli najmä 60. roky"},{"id":2722,"type":"single","question":"Ako sa vyvíjala slovenská dráma v 50. rokoch?","options":["Vznikali komédie, veselohry aj schematické ideologické diela","Prevažovala len absurdná dráma","Písali sa len historické tragédie","Divadlá prestali fungovať"],"correctAnswer":"Vznikali komédie, veselohry aj schematické ideologické diela"},{"id":2723,"type":"single","question":"Čo bolo typické pre drámu 60. rokov?","options":["Dôraz na individualitu a väčšiu umeleckú slobodu","Návrat ku klasicistickým pravidlám","Úplné podriadenie budovateľskej ideológii","Zánik autorských divadiel"],"correctAnswer":"Dôraz na individualitu a väčšiu umeleckú slobodu"},{"id":2724,"type":"single","question":"Čo sa stalo s mnohými dramatikmi v 70. rokoch?","options":["Museli sa odmlčať alebo boli vytlačení do úzadia","Získali úplnú tvorivú slobodu","Presťahovali sa všetci do zahraničia","Písali už len poéziu"],"correctAnswer":"Museli sa odmlčať alebo boli vytlačení do úzadia"},{"id":2725,"type":"single","question":"Čo je replika?","options":["Prehovor postavy v dramatickom texte","Autorská poznámka v zátvorke","Názov celej drámy","Opis scény na javisku"],"correctAnswer":"Prehovor postavy v dramatickom texte"},{"id":2726,"type":"single","question":"Čo je scénická poznámka?","options":["Autorská poznámka usmerňujúca javiskové konanie","Vnútorný monológ postavy","Dialóg dvoch postáv","Záverečné hodnotenie diela"],"correctAnswer":"Autorská poznámka usmerňujúca javiskové konanie"},{"id":2727,"type":"single","question":"Prečo sú ukážky z drámy dramatickými textami?","options":["Sú určené na javiskové stvárnenie a majú dialógy","Sú písané iba vo veršoch","Vždy ich rozpráva jeden rozprávač","Obsahujú len opisy prírody"],"correctAnswer":"Sú určené na javiskové stvárnenie a majú dialógy"},{"id":2728,"type":"single","question":"Kto je autorom hry Kým kohút nezaspieva?","options":["Ivan Bukovčan","Peter Karvaš","Samuel Beckett","Stanislav Štepka"],"correctAnswer":"Ivan Bukovčan"},{"id":2729,"type":"single","question":"Aký charakter má hra Kým kohút nezaspieva?","options":["Dráma s prvkami existencializmu a morálnym rozmerom","Čistá veselohra bez vážnej témy","Historická kronika vo veršoch","Absurdná dráma bez vojnového pozadia"],"correctAnswer":"Dráma s prvkami existencializmu a morálnym rozmerom"},{"id":2730,"type":"single","question":"Aká je hlavná situácia v hre Kým kohút nezaspieva?","options":["Desiati ľudia v pivnici čelia hraničnej voľbe počas vojny","Rodina sa sťahuje do mesta po vojne","Dvaja klauni vedú kabaretný dialóg","Divadelníci nacvičujú zákazané predstavenie"],"correctAnswer":"Desiati ľudia v pivnici čelia hraničnej voľbe počas vojny"},{"id":2731,"type":"single","question":"Čo znamená názov Kým kohút nezaspieva?","options":["Naráža na opakované zrady človeka","Označuje začiatok nového dňa bez významu","Je to doslovná poľnohospodárska poznámka","Vyjadruje komický refrén hry"],"correctAnswer":"Naráža na opakované zrady človeka"},{"id":2732,"type":"single","question":"Kto sa spája s Divadlom na korze?","options":["Milan Lasica a Július Satinský","Ivan Bukovčan a Peter Karvaš","Ján Chalupka a Ján Palárik","Samuel Beckett a Ionesco"],"correctAnswer":"Milan Lasica a Július Satinský"},{"id":2733,"type":"multiple","question":"Čím bolo typické autorské divadlo Lasicu a Satinského?","options":["poetikou nonsensu","paradoxom a slovnými hrami","kritikou spoločenských pomerov","kabaretnou formou","smiechom cez slzy","čistým socialistickým realizmom"],"correctAnswer":["poetikou nonsensu","paradoxom a slovnými hrami","kritikou spoločenských pomerov","kabaretnou formou","smiechom cez slzy"]},{"id":2734,"type":"single","question":"Čo je Soaré?","options":["Kabaretné predstavenie Lasicu a Satinského","Historická hra Ivana Bukovčana","Absurdná dráma Petra Karvaša","Prvá hra Radošinského naivného divadla"],"correctAnswer":"Kabaretné predstavenie Lasicu a Satinského"},{"id":2735,"type":"multiple","question":"Aké postupy využívali Lasica a Satinský vo svojich dielach?","options":["postupy absurdnej hry","paradox","pointu","paródiu","dekompozíciu","poetiku klaunov"],"correctAnswer":["postupy absurdnej hry","paradox","pointu","paródiu","dekompozíciu","poetiku klaunov"]},{"id":2736,"type":"single","question":"Čo je Radošinské naivné divadlo?","options":["Slovenský autorský divadelný súbor spojený so Stanislavom Štepkom","Profesionálne divadlo založené v Prahe","Absurdné divadlo bez stáleho autora","Kabaretný projekt Lasicu a Satinského"],"correctAnswer":"Slovenský autorský divadelný súbor spojený so Stanislavom Štepkom"},{"id":2737,"type":"multiple","question":"Čím sú typické hry Stanislava Štepku a Radošincov?","options":["originálnym humorom","satirou","drobnými hrdinami","radošinským nárečím","montážou scénok a pesničiek","prísnou antickou kompozíciou"],"correctAnswer":["originálnym humorom","satirou","drobnými hrdinami","radošinským nárečím","montážou scénok a pesničiek"]},{"id":2738,"type":"multiple","question":"Ktoré tvrdenia o slovenskej dráme po roku 1945 sú správne?","options":["po vojne sa rozšírila sieť divadelných scén","v 60. rokoch sa dramatici inšpirovali aj existencializmom a absurdnou drámou","v 70. rokoch mali všetci dramatici úplnú slobodu","vznikli autorské divadlá","po roku 1989 vznikali aj alternatívne divadlá"],"correctAnswer":["po vojne sa rozšírila sieť divadelných scén","v 60. rokoch sa dramatici inšpirovali aj existencializmom a absurdnou drámou","vznikli autorské divadlá","po roku 1989 vznikali aj alternatívne divadlá"]},{"id":2739,"type":"matching","question":"Priraď autora alebo súbor k dielu či charakteristike.","pairs":[{"term":"Ivan Bukovčan","match":"Kým kohút nezaspieva"},{"term":"Lasica a Satinský","match":"Soaré"},{"term":"Stanislav Štepka / Radošinské naivné divadlo","match":"Človečina / Jááánošííík"}],"correctAnswer":{"Ivan Bukovčan":"Kým kohút nezaspieva","Lasica a Satinský":"Soaré","Stanislav Štepka / Radošinské naivné divadlo":"Človečina / Jááánošííík"}},{"id":2740,"type":"ordering","question":"Usporiadaj základný vývin slovenskej drámy po roku 1945.","options":["schematické 50. roky","uvoľnenejšie a tvorivé obdobie","normalizačné obmedzenia","alternatívne a nové divadlá po roku 1989"],"correctAnswer":["schematické 50. roky","uvoľnenejšie a tvorivé 60. roky","normalizačné obmedzenia 70. rokov","alternatívne a nové divadlá po roku 1989"]}]