[{"themeId":1,"themeName":"Informácia / Literatúra ako umenie","questionCount":40},{"themeId":2,"themeName":"Komunikácia / Staroveká literatúra (Antigona)","questionCount":40},{"themeId":3,"themeName":"Jazyky / Cyril a Metod","questionCount":40},{"themeId":4,"themeName":"Úvaha / Humanizmus a renesancia (Hamlet)","questionCount":37},{"themeId":5,"themeName":"Slovné druhy / Barok (Hugolín Gavlovič)","questionCount":41},{"themeId":6,"themeName":"Veta / Klasicizmus (Moliére - Lakomec)","questionCount":39},{"themeId":7,"themeName":"Bernolák, Štúr / Klasicizmus, Hollý, Kollár","questionCount":40},{"themeId":8,"themeName":"Charakteristika / Romantizmus, Chrám Matky Božej v Paríži, Kapitánova dcéra","questionCount":40},{"themeId":9,"themeName":"Rečnícky štýl / Slovenská preromantická a romantická literatúra, Štúrovci","questionCount":40},{"themeId":10,"themeName":"Národný jazyk / Štúrovci, Marína, Mor ho!","questionCount":30},{"themeId":11,"themeName":"Lexika / Lyrika","questionCount":32},{"themeId":12,"themeName":"Administratívny štýl / Existencializmus, Beat Generation","questionCount":30},{"themeId":13,"themeName":"Jazykové štýly / Socialistický realizmus","questionCount":30},{"themeId":14,"themeName":"Neohybné slovné druhy / Realizmus vo svetovej literatúre","questionCount":40},{"themeId":15,"themeName":"Frazeologizmy / Slovenský realizmus, Ťapákovci, Maco Mlieč","questionCount":40},{"themeId":16,"themeName":"Slohové postupy / Pavol Országh Hviezdoslav","questionCount":20},{"themeId":17,"themeName":"Prozodické vlastnosti / Literárna moderna","questionCount":12},{"themeId":18,"themeName":"Spodobovanie / Slovenské divadlo","questionCount":12},{"themeId":19,"themeName":"Slovotvorba / Na západe nič nového, Živý bič","questionCount":37},{"themeId":20,"themeName":"Umelecký štýl / Avantgarda","questionCount":39},{"themeId":21,"themeName":"Súvetie / Naturizmus, Drak sa vracia, Tri gaštanové kone","questionCount":36},{"themeId":22,"themeName":"Opisný slohový postup / Expresionizmus, Jozef Mak, Matka","questionCount":40},{"themeId":23,"themeName":"Publicistický štýl / Slovenská poézia po roku 1945, Rúfus, Válek","questionCount":40},{"themeId":24,"themeName":"Rozprávací slohový postup / Kto chytá v žite","questionCount":40},{"themeId":25,"themeName":"Vetné členy / Kolíska, Ako chutí moc","questionCount":42},{"themeId":26,"themeName":"Veľké písmená / Absurdná dráma","questionCount":40},{"themeId":27,"themeName":"Beletrizovaný životopis / Slovenská dráma po roku 1945","questionCount":40},{"themeId":28,"themeName":"Interview, diskusný príspevok, príležitostný prejav / Ivan Krasko","questionCount":36},{"themeId":29,"themeName":"Zámená, číslovky, slovesá / Sumerská a hebrejská literatúra","questionCount":50},{"themeId":30,"themeName":"Dejiny slovenského jazyka od roku 863 / Balada","questionCount":52}]